verify_ai/__init__.py
verify_ai/cli.py
verify_ai/config.py
verify_ai/analysis/__init__.py
verify_ai/analysis/analyzer.py
verify_ai/analysis/fixer.py
verify_ai/core/__init__.py
verify_ai/core/generator.py
verify_ai/core/scanner.py
verify_ai/coverage/__init__.py
verify_ai/coverage/analyzer.py
verify_ai/coverage/collectors.py
verify_ai/coverage/models.py
verify_ai/coverage/reporter.py
verify_ai/dashboard/__init__.py
verify_ai/dashboard/app.py
verify_ai/dashboard/models.py
verify_ai/dashboard/routes.py
verify_ai/dashboard/storage.py
verify_ai/dashboard/static/index.html
verify_ai/dashboard/static/css/style.css
verify_ai/dashboard/static/js/dashboard.js
verify_ai/git/__init__.py
verify_ai/git/strategy.py
verify_ai/git/tracker.py
verify_ai/llm/__init__.py
verify_ai/llm/base.py
verify_ai/llm/claude.py
verify_ai/llm/factory.py
verify_ai/llm/ollama_client.py
verify_ai/llm/openai_client.py
verify_ai/llm/prompts/__init__.py
verify_ai/mcp/__init__.py
verify_ai/mcp/server.py
verify_ai/parsers/__init__.py
verify_ai/parsers/code_parser.py
verify_ai/parsers/openapi.py
verify_ai/parsers/tree_sitter_parser.py
verify_ai/scenario/__init__.py
verify_ai/scenario/api_logs.py
verify_ai/scenario/error_replay.py
verify_ai/scenario/har_parser.py
verify_ai/server/__init__.py
verify_ai/server/api.py
verify_ai/server/webhook.py
verify_ai-0.1.0.dist-info/METADATA
verify_ai-0.1.0.dist-info/WHEEL
verify_ai-0.1.0.dist-info/entry_points.txt
verify_ai-0.1.0.dist-info/licenses/LICENSE
verify_ai-0.1.0.dist-info/RECORD
