Metadata-Version: 2.4
Name: verify-ai
Version: 0.1.0
Summary: AI-powered automated verification system for code quality
Project-URL: Homepage, https://github.com/ikane001/VerifyAI
Project-URL: Documentation, https://github.com/ikane001/VerifyAI#readme
Project-URL: Repository, https://github.com/ikane001/VerifyAI
Author-email: ikane <ikane12048@163.com>
License-Expression: MIT
License-File: LICENSE
Keywords: ai,automation,code-quality,llm,testing
Classifier: Development Status :: 3 - Alpha
Classifier: Intended Audience :: Developers
Classifier: License :: OSI Approved :: MIT License
Classifier: Programming Language :: Python :: 3
Classifier: Programming Language :: Python :: 3.11
Classifier: Programming Language :: Python :: 3.12
Classifier: Topic :: Software Development :: Testing
Requires-Python: >=3.11
Requires-Dist: anthropic>=0.18.0
Requires-Dist: coverage>=7.0.0
Requires-Dist: gitpython>=3.1.0
Requires-Dist: httpx>=0.25.0
Requires-Dist: ollama>=0.1.0
Requires-Dist: openai>=1.10.0
Requires-Dist: openapi-spec-validator>=0.7.0
Requires-Dist: prance>=23.0.0
Requires-Dist: pydantic-settings>=2.0.0
Requires-Dist: pydantic>=2.0.0
Requires-Dist: pyyaml>=6.0.0
Requires-Dist: rich>=13.0.0
Requires-Dist: tree-sitter-go>=0.21.0
Requires-Dist: tree-sitter-java>=0.21.0
Requires-Dist: tree-sitter-javascript>=0.21.0
Requires-Dist: tree-sitter-python>=0.21.0
Requires-Dist: tree-sitter-typescript>=0.21.0
Requires-Dist: tree-sitter>=0.21.0
Requires-Dist: typer>=0.9.0
Provides-Extra: all
Requires-Dist: aiosqlite>=0.19.0; extra == 'all'
Requires-Dist: celery>=5.3.0; extra == 'all'
Requires-Dist: fastapi>=0.109.0; extra == 'all'
Requires-Dist: mypy>=1.8.0; extra == 'all'
Requires-Dist: pytest-asyncio>=0.23.0; extra == 'all'
Requires-Dist: pytest-cov>=4.0.0; extra == 'all'
Requires-Dist: pytest>=8.0.0; extra == 'all'
Requires-Dist: redis>=5.0.0; extra == 'all'
Requires-Dist: ruff>=0.2.0; extra == 'all'
Requires-Dist: textual>=0.50.0; extra == 'all'
Requires-Dist: uvicorn>=0.27.0; extra == 'all'
Provides-Extra: dashboard
Requires-Dist: aiosqlite>=0.19.0; extra == 'dashboard'
Requires-Dist: fastapi>=0.109.0; extra == 'dashboard'
Requires-Dist: uvicorn>=0.27.0; extra == 'dashboard'
Provides-Extra: dev
Requires-Dist: mypy>=1.8.0; extra == 'dev'
Requires-Dist: pytest-asyncio>=0.23.0; extra == 'dev'
Requires-Dist: pytest-cov>=4.0.0; extra == 'dev'
Requires-Dist: pytest>=8.0.0; extra == 'dev'
Requires-Dist: ruff>=0.2.0; extra == 'dev'
Provides-Extra: server
Requires-Dist: celery>=5.3.0; extra == 'server'
Requires-Dist: fastapi>=0.109.0; extra == 'server'
Requires-Dist: redis>=5.0.0; extra == 'server'
Requires-Dist: uvicorn>=0.27.0; extra == 'server'
Provides-Extra: tui
Requires-Dist: textual>=0.50.0; extra == 'tui'
